CONTRIBUTING.md
LICENSE
MANIFEST.in
README.md
settings.ini
setup.py
theguardianscraper/Db_Config.py
theguardianscraper/__init__.py
theguardianscraper/_nbdev.py
theguardianscraper/extractor.py
theguardianscraper/mapper.py
theguardianscraper/parser.py
theguardianscraper/scraper.py
theguardianscraper.egg-info/PKG-INFO
theguardianscraper.egg-info/SOURCES.txt
theguardianscraper.egg-info/dependency_links.txt
theguardianscraper.egg-info/entry_points.txt
theguardianscraper.egg-info/not-zip-safe
theguardianscraper.egg-info/requires.txt
theguardianscraper.egg-info/top_level.txt
theguardianscraper/config/__init__.py
theguardianscraper/config/localconfig.py
theguardianscraper/config/mongo.py
theguardianscraper/models/__init__.py
theguardianscraper/models/fixture.py
theguardianscraper/models/preview.py